ff_five9_python-0.0.4.dev6.dist-info/licenses/LICENSE
five9/__init__.py
five9/api/__init__.py
five9/api/classic_restadmin/__init__.py
five9/api/classic_restadmin/common_objects.py
five9/api/classic_restadmin/restadmin_classic_client.py
five9/api/classic_restadmin/vcc_prompts_classic.py
five9/api/restadmin/__init__.py
five9/api/restadmin/base_client.py
five9/api/restadmin/cav.py
five9/api/restadmin/context_services.py
five9/api/restadmin/restadmin_client.py
five9/api/restadmin/speed_dials.py
five9/api/restadmin/vcc_prompts.py
five9/api/studio/__init__.py
five9/api/studio/base_client.py
five9/api/studio/client_v6.py
five9/api/studio/v6_datastores.py
five9/api/studio/v6_prompts.py
five9/api/studio/v6_tasks.py
five9/api/supervisor/client_supervisor.py
five9/api_v2/base_client.py
five9/models/__init__.py
five9/models/cav.py
five9/models/common.py
five9/models/context_services_model.py
five9/models/five9_prompts.py
five9/models/query_filter.py
five9/models/speed_dials.py
five9/models/vcc_domain.py
five9/models/vcc_general.py
five9/vcc_domain/five9_domain.py
ff_five9_python-0.0.4.dev6.dist-info/METADATA
ff_five9_python-0.0.4.dev6.dist-info/WHEEL
ff_five9_python-0.0.4.dev6.dist-info/top_level.txt
ff_five9_python-0.0.4.dev6.dist-info/RECORD
